py_ask_sdk_test
