Metadata-Version: 2.1
Name: py-ask-sdk-test
Version: 1.1
Summary: A framework for testing Alexa Skills developed in Python with the alexa-skills-kit-sdk-for-python.
Home-page: https://github.com/BananaNosh/py_ask_sdk_test
Author: Jonathan Loos
Author-email: loos.jonathan.martin@gmail.com
License: MIT
Download-URL: https://github.com/BananaNosh/py_ask_sdk_test/archive/v1.1.tar.gz
Keywords: alexa,skill,alexa skill,test,testing,framework,testing framework,ask_sdk,python,pytest
Platform: UNKNOWN
Classifier: Development Status :: 5 - Production/Stable
Classifier: Intended Audience :: Developers
Classifier: Topic :: Software Development :: Build Tools
Classifier: License :: OSI Approved :: MIT License
Classifier: Programming Language :: Python :: 3.6
